azkm/__init__.py
azkm/__main__.py
azkm/cdktf.json
azkm/commands/__init__.py
azkm/commands/dataset.py
azkm/commands/deploy.py
azkm/commands/destroy.py
azkm/commands/environment.py
azkm/commands/environments.py
azkm/commands/init.py
azkm/commands/recipe.py
azkm/commands/state.py
azkm/flight_checks/__init__.py
azkm/flight_checks/prereqs.py
azkm/providers/__init__.py
azkm/providers/azurerm/__init__.py
azkm/providers/azurerm/_jsii/__init__.py
azkm/providers/azurerm/_jsii/azurerm@0.0.0.jsii.tgz
azkm/utils/__init__.py
azkm/utils/aks.py
azkm/utils/az.py
azkm/utils/cogsearch.py
azkm/utils/osutil.py
azkm/utils/stdout.py
azkm/utils/text.py
azkm/utils/tf.py
azure_knowledgemining_cli-0.1.0.dist-info/LICENSE
azure_knowledgemining_cli-0.1.0.dist-info/METADATA
azure_knowledgemining_cli-0.1.0.dist-info/WHEEL
azure_knowledgemining_cli-0.1.0.dist-info/entry_points.txt
azure_knowledgemining_cli-0.1.0.dist-info/top_level.txt
azure_knowledgemining_cli-0.1.0.dist-info/RECORD
