Metadata-Version: 2.1
Name: azure-knowledgemining-cli
Version: 0.1.0
Summary: UNKNOWN
Home-page: https://github.com/frogrammer/azure-knowledgemining-cli
Author: Luke Vinton
Author-email: luke0vinton@gmail.com
License: Apache 2.0
Platform: UNKNOWN
Requires-Dist: fire
Requires-Dist: fire-cli-helper
Requires-Dist: cdktf
Requires-Dist: tabulate
Requires-Dist: azure-cli (==2.14.0)
Requires-Dist: azure-mgmt-core (==1.2.0)
Requires-Dist: azure-storage-blob
Requires-Dist: clint
